braumeister/__init__.py
braumeister/__main__.py
braumeister/braumeister.py
braumeister/builder.py
braumeister/core.py
braumeister/git.py
braumeister/jira.py
braumeister/settings.py
braumeister/setup.py
braumeister/state.py
braumeister/actions/__init__.py
braumeister/actions/candidate.py
braumeister/actions/cleanup.py
braumeister/actions/finalize.py
braumeister/actions/nightly.py
braumeister/actions/release.py
braumeister-0.5.0.dist-info/LICENSE
braumeister-0.5.0.dist-info/METADATA
braumeister-0.5.0.dist-info/WHEEL
braumeister-0.5.0.dist-info/entry_points.txt
braumeister-0.5.0.dist-info/top_level.txt
braumeister-0.5.0.dist-info/RECORD
