Metadata-Version: 2.1
Name: braumeister
Version: 0.5.0
Summary: Easy release bulding, combining JIRA and git
Home-page: https://www.talentsconnect.com
Author: Marcel Steffen
Author-email: marcel@talentsconnect.com
License: MIT
Keywords: git jira release
Classifier: Development Status :: 4 - Beta
Classifier: Environment :: Console
Classifier: Intended Audience :: Developers
Classifier: Topic :: Utilities
Classifier: Topic :: Software Development :: Version Control :: Git
Requires-Python: !=2.7, !=3.4, >=3.5
License-File: LICENSE
Requires-Dist: requests
Requires-Dist: colorama
